nonebot_plugin_baize-1.2.0.dist-info/METADATA
nonebot_plugin_baize-1.2.0.dist-info/WHEEL
nonebot_plugin_baize-1.2.0.dist-info/entry_points.txt
nonebot_plugin_baize-1.2.0.dist-info/licenses/LICENSE
nonebot_plugin_baize/__init__.py
nonebot_plugin_baize/__main__.py
nonebot_plugin_baize/config.py
nonebot_plugin_baize/questions.json
nonebot_plugin_baize-1.2.0.dist-info/RECORD
