Metadata-Version: 2.1
Name: nonebot-plugin-baize
Version: 1.2.0
Summary: 基于白泽神话的群验证插件
Author-Email: afterow <afterow@163.com>
License: MIT License
Classifier: Framework :: Pydantic
Classifier: License :: OSI Approved :: MIT License
Classifier: Programming Language :: Python :: 3
Classifier: Programming Language :: Python :: 3 :: Only
Classifier: Programming Language :: Python :: 3.9
Classifier: Programming Language :: Python :: 3.10
Classifier: Programming Language :: Python :: 3.11
Classifier: Natural Language :: Chinese (Simplified)
Project-URL: Homepage, https://github.com/afterow/nonebot-plugin-baize
Project-URL: Bug Tracker, https://github.com/afterow/nonebot-plugin-baize/issues
Requires-Python: <4.0,>=3.9
Requires-Dist: nonebot-adapter-onebot>=2.4.6
Requires-Dist: nonebot2>=2.3
